zhipuai_pydantic_v1/__init__.py
zhipuai_pydantic_v1/__version__.py
zhipuai_pydantic_v1/_client.py
zhipuai_pydantic_v1/api_resource/__init__.py
zhipuai_pydantic_v1/api_resource/chat/__init__.py
zhipuai_pydantic_v1/api_resource/chat/async_completions.py
zhipuai_pydantic_v1/api_resource/chat/chat.py
zhipuai_pydantic_v1/api_resource/chat/completions.py
zhipuai_pydantic_v1/api_resource/embeddings.py
zhipuai_pydantic_v1/api_resource/files.py
zhipuai_pydantic_v1/api_resource/fine_tuning/__init__.py
zhipuai_pydantic_v1/api_resource/fine_tuning/fine_tuning.py
zhipuai_pydantic_v1/api_resource/fine_tuning/jobs.py
zhipuai_pydantic_v1/api_resource/images.py
zhipuai_pydantic_v1/core/__init__.py
zhipuai_pydantic_v1/core/_base_api.py
zhipuai_pydantic_v1/core/_base_type.py
zhipuai_pydantic_v1/core/_errors.py
zhipuai_pydantic_v1/core/_files.py
zhipuai_pydantic_v1/core/_http_client.py
zhipuai_pydantic_v1/core/_jwt_token.py
zhipuai_pydantic_v1/core/_request_opt.py
zhipuai_pydantic_v1/core/_response.py
zhipuai_pydantic_v1/core/_sse_client.py
zhipuai_pydantic_v1/core/_utils.py
zhipuai_pydantic_v1/pydantic_v1/__init__.py
zhipuai_pydantic_v1/types/__init__.py
zhipuai_pydantic_v1/types/chat/__init__.py
zhipuai_pydantic_v1/types/chat/async_chat_completion.py
zhipuai_pydantic_v1/types/chat/chat_completion.py
zhipuai_pydantic_v1/types/chat/chat_completion_chunk.py
zhipuai_pydantic_v1/types/chat/chat_completions_create_param.py
zhipuai_pydantic_v1/types/embeddings.py
zhipuai_pydantic_v1/types/file_object.py
zhipuai_pydantic_v1/types/fine_tuning/__init__.py
zhipuai_pydantic_v1/types/fine_tuning/fine_tuning_job.py
zhipuai_pydantic_v1/types/fine_tuning/fine_tuning_job_event.py
zhipuai_pydantic_v1/types/fine_tuning/job_create_params.py
zhipuai_pydantic_v1/types/image.py
zhipuai_pydantic_v1-2.0.5.dist-info/METADATA
zhipuai_pydantic_v1-2.0.5.dist-info/WHEEL
zhipuai_pydantic_v1-2.0.5.dist-info/RECORD
