Metadata-Version: 2.1
Name: zhipuai_pydantic_v1
Version: 2.0.5
Summary: downgrade v1 for langchain (zhipu is an SDK library for accessing big model apis from ZhipuAI)
Author: arcstep
Author-email: 43801@qq.com
Requires-Python: >=3.9,<4.0
Classifier: Programming Language :: Python :: 3
Classifier: Programming Language :: Python :: 3.9
Classifier: Programming Language :: Python :: 3.10
Classifier: Programming Language :: Python :: 3.11
Classifier: Programming Language :: Python :: 3.12
Requires-Dist: cachetools (==4.2.2)
Requires-Dist: httpx (>=0.23.0,<0.24.0)
Requires-Dist: pydantic (>=1,<3)
Requires-Dist: pyjwt (>=2.8.0,<3.0.0)
